r53spflat/__init__.py
r53spflat/cli.py
r53spflat/r53_dns.py
r53spflat-22.2.20.data/scripts/r53spflat
r53spflat-22.2.20.dist-info/LICENSE.txt
r53spflat-22.2.20.dist-info/METADATA
r53spflat-22.2.20.dist-info/WHEEL
r53spflat-22.2.20.dist-info/top_level.txt
r53spflat-22.2.20.dist-info/RECORD
