Metadata-Version: 2.1
Name: r53spflat
Version: 22.2.20
Summary: Flattens SPF records and updates Cloudflare zones
Home-page: https://github.com/Glocktober/r53spflat
Author: gunville
Author-email: rk13088@yahoo.com
License: UNKNOWN
Project-URL: repo, https://github.com/Glocktober/r53spflat.git
Project-URL: overview, https://github.com/Glocktober/r53spflat/blob/master/README.md
Keywords: 'route53 aws dns spf flattener'
Platform: UNKNOWN
Classifier: Programming Language :: Python :: 3
Classifier: License :: OSI Approved :: MIT License
Classifier: Operating System :: OS Independent
Requires-Python: >=3.6
License-File: LICENSE.txt
Requires-Dist: boto3 (>=1.21.2)
Requires-Dist: sender-policy-flattener (==0.3.1)
